{
  "week_number": 11,
  "pushes": [
    {
      "timestamp": "2025-08-02T12:10:25.739305+08:00",
      "fingerprint": [
        "炼气十万年||264",
        "妖神记<font size='2' color='red'>（下集预告）</font>||390",
        "万界独尊||352",
        "妖神记<font size='2' color='red'>（下集预告）</font>||389",
        "Multi Sub【诡秘之主 | Lord of Mysteries | Episode 07 巧合||07",
        "Preview【诡秘之主 | Lord of Mysteries | Episode 08<font size='2' color='red'>（下集预告）</font>||08",
        "凡人修仙传||154",
        "万界独尊<font size='2' color='red'>（下集预告）</font>||353",
        "凡人修仙传<font size='2' color='red'>（下集预告）</font>||155",
        "炼气十万年<font size='2' color='red'>（下集预告）</font>||265"
      ]
    },
    {
      "timestamp": "2025-08-03T12:34:02.411728+08:00",
      "fingerprint": [
        "魔天记||10",
        "在下“英台”<font size='2' color='red'>（下集预告）</font>||05",
        "在下“英台”||04",
        "魔天记<font size='2' color='red'>（下集预告）</font>||11",
        "牧神记<font size='2' color='red'>（下集预告）</font>||43",
        "凡人修仙传<font size='2' color='red'>（下集预告）</font>||155",
        "武神主宰||569",
        "武神主宰<font size='2' color='red'>（下集预告）</font>||570",
        "凡人修仙传||154",
        "牧神记||42"
      ]
    },
    {
      "timestamp": "2025-08-03T21:21:53.353865+08:00",
      "fingerprint": [
        "大猿魂<font size='2' color='red'>（下集预告）</font>||12",
        "在下“英台”<font size='2' color='red'>（下集预告）</font>||05",
        "大猿魂||11",
        "仙逆 4k||100",
        "武神主宰||569",
        "仙逆||100",
        "仙逆<font size='2' color='red'>（下集预告）</font>||101",
        "牧神记||42",
        "武神主宰<font size='2' color='red'>（下集预告）</font>||570",
        "牧神记<font size='2' color='red'>（下集预告）</font>||43"
      ]
    },
    {
      "timestamp": "2025-08-04T12:42:37.499160+08:00",
      "fingerprint": [
        "无上神帝<font size='2' color='red'>（下集预告）</font>||515",
        "万剑王座||01",
        "逆天至尊||433",
        "吞天记||31",
        "无上神帝||514",
        "逆天至尊||430",
        "逆天至尊<font size='2' color='red'>（下集预告）</font>||434",
        "在下“英台”<font size='2' color='red'>（下集预告）</font>||06",
        "吞天记<font size='2' color='red'>（下集预告）</font>||32",
        "无上神帝||509"
      ]
    },
    {
      "timestamp": "2025-08-04T19:44:33.522474+08:00",
      "fingerprint": [
        "吞噬星空<font size='2' color='red'>（下集预告）</font>||184",
        "无上神帝||509",
        "无上神帝<font size='2' color='red'>（下集预告）</font>||515",
        "吞噬星空||183",
        "吞噬星空 4k||183",
        "逆天至尊||430",
        "万剑王座||01",
        "遮天 4k||101",
        "吞天记||31",
        "吞天记<font size='2' color='red'>（下集预告）</font>||32"
      ]
    },
    {
      "timestamp": "2025-08-05T12:34:19.449491+08:00",
      "fingerprint": [
        "武神主宰<font size='2' color='red'>（下集预告）</font>||571",
        "万界独尊<font size='2' color='red'>（下集预告）</font>||354",
        "灵剑尊||616",
        "灵剑尊||619",
        "灵剑尊<font size='2' color='red'>（下集预告）</font>||620",
        "炼气十万年||265",
        "武神主宰||570",
        "炼气十万年<font size='2' color='red'>（下集预告）</font>||266",
        "炼气十万年||260",
        "万界独尊||349"
      ]
    },
    {
      "timestamp": "2025-08-05T19:45:13.579190+08:00",
      "fingerprint": [
        "遮天<font size='2' color='red'>（下集预告）</font>||122",
        "紫川 4k||04",
        "遮天||121",
        "紫川||04",
        "灵剑尊||616",
        "武神主宰<font size='2' color='red'>（下集预告）</font>||571",
        "遮天<font size='2' color='red'>（下集预告）</font>||123",
        "武神主宰||570",
        "遮天 4k||121",
        "紫川<font size='2' color='red'>（下集预告）</font>||05"
      ]
    },
    {
      "timestamp": "2025-08-06T12:31:14.618678+08:00",
      "fingerprint": [
        "缥缈剑仙传||02",
        "双生武魂||10",
        "缥缈剑仙传||03",
        "吞天记<font size='2' color='red'>（下集预告）</font>||33",
        "吞天记||32",
        "缥缈剑仙传||05",
        "缥缈剑仙传||04",
        "缥缈剑仙传||01",
        "缥缈剑仙传<font size='2' color='red'>（下集预告）</font>||06"
      ]
    },
    {
      "timestamp": "2025-08-06T21:30:19.553753+08:00",
      "fingerprint": [
        "神印王座 4k||171",
        "缥缈剑仙传<font size='2' color='red'>（下集预告）</font>||06",
        "神印王座<font size='2' color='red'>（下集预告）</font>||172",
        "缥缈剑仙传||05",
        "双生武魂||10",
        "诛仙 4k||11",
        "缥缈剑仙传||01",
        "诛仙||11",
        "神印王座||171",
        "诛仙<font size='2' color='red'>（下集预告）</font>||12"
      ]
    },
    {
      "timestamp": "2025-08-07T12:31:07.810035+08:00",
      "fingerprint": [
        "妖神记<font size='2' color='red'>（下集预告）</font>||390",
        "缥缈剑仙传<font size='2' color='red'>（下集预告）</font>||06",
        "缥缈剑仙传||05",
        "妖神记<font size='2' color='red'>（下集预告）</font>||391",
        "双生武魂||10",
        "缥缈剑仙传||01",
        "双生武魂<font size='2' color='red'>（下集预告）</font>||15",
        "缥缈剑仙传||04",
        "双生武魂||14",
        "妖神记||389"
      ]
    }
  ]
}