{
  "week_number": 11,
  "pushes": [
    {
      "timestamp": "2025-06-10T19:42:02.687635+08:00",
      "fingerprint": [
        "一念永恒<font size='2' color='red'>（下集预告）</font>||54",
        "炼气十万年<font size='2' color='red'>（下集预告）</font>||249",
        "炼气十万年||248",
        "大侠请上攻<font size='2' color='red'>（下集预告）</font>||07",
        "万界独尊<font size='2' color='red'>（下集预告）</font>||338",
        "万界独尊||337",
        "遮天||113",
        "遮天<font size='2' color='red'>（下集预告）</font>||114",
        "灵剑尊<font size='2' color='red'>（下集预告）</font>||604",
        "一念永恒||53"
      ]
    },
    {
      "timestamp": "2025-06-10T21:22:15.367186+08:00",
      "fingerprint": [
        "遮天 4k||113",
        "一念永恒||53",
        "万界独尊<font size='2' color='red'>（下集预告）</font>||338",
        "大侠请上攻<font size='2' color='red'>（下集预告）</font>||07",
        "遮天<font size='2' color='red'>（下集预告）</font>||114",
        "一念永恒 4k||53",
        "一念永恒<font size='2' color='red'>（下集预告）</font>||54",
        "炼气十万年||248",
        "遮天||113",
        "炼气十万年<font size='2' color='red'>（下集预告）</font>||249"
      ]
    },
    {
      "timestamp": "2025-06-11T15:37:48.296043+08:00",
      "fingerprint": [
        "遮天 4k||113",
        "吞天记||11",
        "万界独尊<font size='2' color='red'>（下集预告）</font>||338",
        "炼气十万年||248",
        "遮天<font size='2' color='red'>（下集预告）</font>||114",
        "炼气十万年<font size='2' color='red'>（下集预告）</font>||249",
        "吞天记<font size='2' color='red'>（下集预告）</font>||12",
        "万界独尊||337",
        "灵剑尊||603",
        "遮天||113"
      ]
    },
    {
      "timestamp": "2025-06-11T19:41:53.903631+08:00",
      "fingerprint": [
        "万界独尊<font size='2' color='red'>（下集预告）</font>||338",
        "神印王座<font size='2' color='red'>（下集预告）</font>||164",
        "遮天 4k||113",
        "神印王座||163",
        "遮天||113",
        "遮天<font size='2' color='red'>（下集预告）</font>||114",
        "炼气十万年<font size='2' color='red'>（下集预告）</font>||249",
        "吞天记||11",
        "炼气十万年||248",
        "吞天记<font size='2' color='red'>（下集预告）</font>||12"
      ]
    },
    {
      "timestamp": "2025-06-11T21:21:54.410991+08:00",
      "fingerprint": [
        "神印王座<font size='2' color='red'>（下集预告）</font>||164",
        "诛仙||",
        "遮天 4k||113",
        "遮天||113",
        "遮天<font size='2' color='red'>（下集预告）</font>||114",
        "吞天记<font size='2' color='red'>（下集预告）</font>||12",
        "神印王座||163",
        "吞天记||11",
        "炼气十万年<font size='2' color='red'>（下集预告）</font>||249",
        "神印王座 4k||163"
      ]
    },
    {
      "timestamp": "2025-06-12T12:01:12.567116+08:00",
      "fingerprint": [
        "神印王座<font size='2' color='red'>（下集预告）</font>||164",
        "诛仙||01",
        "鲲吞天下之掌门归来||08",
        "小仙之瑶||19",
        "诛仙||",
        "吞天记<font size='2' color='red'>（下集预告）</font>||12",
        "诛仙||03",
        "神印王座 4k||163",
        "诛仙<font size='2' color='red'>（下集预告）</font>||04",
        "诛仙||02"
      ]
    },
    {
      "timestamp": "2025-06-12T15:37:45.624482+08:00",
      "fingerprint": [
        "神印王座<font size='2' color='red'>（下集预告）</font>||164",
        "诛仙||",
        "诛仙<font size='2' color='red'>（下集预告）</font>||04",
        "小仙之瑶||19",
        "诛仙||02",
        "诛仙||03",
        "诛仙||01",
        "鲲吞天下之掌门归来||08",
        "吞天记<font size='2' color='red'>（下集预告）</font>||12"
      ]
    },
    {
      "timestamp": "2025-06-12T19:42:01.710952+08:00",
      "fingerprint": [
        "完美世界||219",
        "完美世界||220",
        "诛仙||03",
        "诛仙<font size='2' color='red'>（下集预告）</font>||04",
        "诛仙||02",
        "鲲吞天下之掌门归来||08",
        "诛仙||01",
        "吞天记<font size='2' color='red'>（下集预告）</font>||12",
        "完美世界||221"
      ]
    },
    {
      "timestamp": "2025-06-12T21:21:32.918464+08:00",
      "fingerprint": [
        "诛仙<font size='2' color='red'>（下集预告）</font>||04",
        "诛仙||03",
        "诛仙||01",
        "完美世界 4k||219",
        "完美世界||220",
        "鲲吞天下之掌门归来||08",
        "完美世界||219",
        "完美世界||221",
        "诛仙||02"
      ]
    },
    {
      "timestamp": "2025-06-13T12:01:35.238086+08:00",
      "fingerprint": [
        "灵剑尊<font size='2' color='red'>（下集预告）</font>||605",
        "无上神帝<font size='2' color='red'>（下集预告）</font>||500",
        "灵笼||05",
        "逆天至尊||418",
        "无上神帝||499",
        "斗战天下||45",
        "灵剑尊||604",
        "逆天至尊<font size='2' color='red'>（下集预告）</font>||419",
        "灵笼<font size='2' color='red'>（下集预告）</font>||06",
        "丹道至尊||127"
      ]
    }
  ]
}