{
  "week_number": 11,
  "pushes": [
    {
      "timestamp": "2025-07-28T19:44:57.221717+08:00",
      "fingerprint": [
        "万界独尊||第350集",
        "武神主宰||第567集",
        "牧神记||第41集",
        "仙逆||第99集",
        "吞噬星空||第182集"
      ]
    },
    {
      "timestamp": "2025-07-29T12:31:34.836223+08:00",
      "fingerprint": [
        "牧神记||第41集",
        "吞噬星空||第182集",
        "武神主宰||第567集",
        "仙逆||第99集",
        "万界独尊||第351集"
      ]
    },
    {
      "timestamp": "2025-07-29T19:44:38.841998+08:00",
      "fingerprint": [
        "仙逆||第99集",
        "遮天||第120集",
        "吞噬星空||第182集",
        "武神主宰||第567集",
        "万界独尊||第351集"
      ]
    },
    {
      "timestamp": "2025-07-30T12:27:39.875960+08:00",
      "fingerprint": [
        "吞噬星空||第182集",
        "武神主宰||第568集",
        "遮天||第120集",
        "仙逆||第99集",
        "万界独尊||第351集"
      ]
    },
    {
      "timestamp": "2025-07-31T19:45:07.170988+08:00",
      "fingerprint": [
        "遮天||第120集",
        "武神主宰||第568集",
        "吞噬星空||第182集",
        "完美世界||第226集",
        "万界独尊||第351集"
      ]
    },
    {
      "timestamp": "2025-08-01T19:44:42.162502+08:00",
      "fingerprint": [
        "万界独尊||第351集",
        "斗罗大陆2：绝世唐门||第112集",
        "完美世界||第226集",
        "遮天||第120集",
        "武神主宰||第568集"
      ]
    },
    {
      "timestamp": "2025-08-02T12:08:49.706036+08:00",
      "fingerprint": [
        "斗罗大陆2：绝世唐门||第112集",
        "武神主宰||第568集",
        "凡人修仙传||第154集",
        "完美世界||第226集",
        "万界独尊||第352集"
      ]
    },
    {
      "timestamp": "2025-08-02T19:42:52.162219+08:00",
      "fingerprint": [
        "斗罗大陆2：绝世唐门||第112集",
        "斗破苍穹 年番||第158集",
        "万界独尊||第352集",
        "凡人修仙传||第154集",
        "完美世界||第226集"
      ]
    },
    {
      "timestamp": "2025-08-03T12:32:12.352497+08:00",
      "fingerprint": [
        "斗破苍穹 年番||第158集",
        "凡人修仙传||第154集",
        "牧神记||第42集",
        "万界独尊||第352集",
        "斗罗大陆2：绝世唐门||第112集"
      ]
    },
    {
      "timestamp": "2025-08-03T19:44:29.201486+08:00",
      "fingerprint": [
        "牧神记||第42集",
        "凡人修仙传||第154集",
        "斗破苍穹 年番||第158集",
        "武神主宰||第569集",
        "仙逆||第100集"
      ]
    },
    {
      "timestamp": "2025-08-04T19:44:49.372784+08:00",
      "fingerprint": [
        "牧神记||第42集",
        "吞噬星空||第183集",
        "仙逆||第100集",
        "武神主宰||第569集",
        "斗破苍穹 年番||第158集"
      ]
    },
    {
      "timestamp": "2025-08-05T12:32:22.913671+08:00",
      "fingerprint": [
        "吞噬星空||第183集",
        "牧神记||第42集",
        "武神主宰||第569集",
        "万界独尊||第353集",
        "仙逆||第100集"
      ]
    },
    {
      "timestamp": "2025-08-05T19:45:29.184926+08:00",
      "fingerprint": [
        "万界独尊||第353集",
        "遮天||第121集",
        "吞噬星空||第183集",
        "武神主宰||第569集",
        "仙逆||第100集"
      ]
    },
    {
      "timestamp": "2025-08-07T19:45:16.229608+08:00",
      "fingerprint": [
        "遮天||第121集",
        "武神主宰||第569集",
        "完美世界||第227集",
        "吞噬星空||第183集",
        "万界独尊||第353集"
      ]
    },
    {
      "timestamp": "2025-08-08T19:45:07.091061+08:00",
      "fingerprint": [
        "遮天||第121集",
        "万界独尊||第353集",
        "完美世界||第227集",
        "斗罗大陆2：绝世唐门||第113集",
        "吞噬星空||第183集"
      ]
    },
    {
      "timestamp": "2025-08-09T12:02:36.818295+08:00",
      "fingerprint": [
        "万界独尊||第354集",
        "完美世界||第227集",
        "斗罗大陆2：绝世唐门||第113集",
        "凡人修仙传||第155集",
        "遮天||第121集"
      ]
    },
    {
      "timestamp": "2025-08-09T19:41:56.669349+08:00",
      "fingerprint": [
        "斗破苍穹 年番||第159集",
        "完美世界||第227集",
        "万界独尊||第354集",
        "斗罗大陆2：绝世唐门||第113集",
        "凡人修仙传||第155集"
      ]
    },
    {
      "timestamp": "2025-08-10T12:25:17.064430+08:00",
      "fingerprint": [
        "万界独尊||第354集",
        "凡人修仙传||第155集",
        "斗破苍穹 年番||第159集",
        "斗罗大陆2：绝世唐门||第113集",
        "牧神记||第43集"
      ]
    },
    {
      "timestamp": "2025-08-10T19:41:54.253984+08:00",
      "fingerprint": [
        "牧神记||第43集",
        "万界独尊||第354集",
        "武神主宰||第571集",
        "凡人修仙传||第155集",
        "斗破苍穹 年番||第159集"
      ]
    },
    {
      "timestamp": "2025-08-10T21:18:56.161550+08:00",
      "fingerprint": [
        "斗破苍穹 年番||第159集",
        "牧神记||第43集",
        "凡人修仙传||第155集",
        "武神主宰||第571集",
        "仙逆||第101集"
      ]
    }
  ]
}